fcards/__init__.py
fcards/fcards.py
fcards-0.3.1.dist-info/LICENSE
fcards-0.3.1.dist-info/METADATA
fcards-0.3.1.dist-info/WHEEL
fcards-0.3.1.dist-info/entry_points.txt
fcards-0.3.1.dist-info/top_level.txt
fcards-0.3.1.dist-info/RECORD
